mkdocs_plugin_commonmark/__init__.py
mkdocs_plugin_commonmark/mistletoe_interop.py
mkdocs_plugin_commonmark/serializers.py
mkdocs_plugin_commonmark-0.0.4.dist-info/LICENSE
mkdocs_plugin_commonmark-0.0.4.dist-info/METADATA
mkdocs_plugin_commonmark-0.0.4.dist-info/WHEEL
mkdocs_plugin_commonmark-0.0.4.dist-info/entry_points.txt
mkdocs_plugin_commonmark-0.0.4.dist-info/top_level.txt
mkdocs_plugin_commonmark-0.0.4.dist-info/RECORD
