Metadata-Version: 2.1
Name: mkdocs-plugin-commonmark
Version: 0.0.4
Summary: A plugin for MkDocs that monkeypatches to support commonmark via mistletoe.
Home-page: https://github.com/soxhub/mkdocs-plugin-commonmark
Author: Rajiv Makhijani
Author-email: rajiv@auditboard.com
License: BSD
Keywords: mkdocs,plugin,commonmark,mistletoe,markdown
Platform: UNKNOWN
Classifier: License :: OSI Approved :: BSD License
Classifier: Programming Language :: Python :: 3.4
Requires-Python: >=3.4
Requires-Dist: mkdocs (>=1.1.2)
Requires-Dist: Markdown (>=3.2.1)
Requires-Dist: mistletoe (>=0.7.2)
